{
  "schema_version": "tail_wing_solidification_probe.v1",
  "component": "tail_wing",
  "source_fixture": "blackcat_004_origin_vsp3",
  "geometry_provider": "esp_rebuilt",
  "geometry_family": "thin_sheet_lifting_surface",
  "execution_mode": "real_provider_gmsh_heal_solidification_probe_no_su2",
  "source_path": "/Volumes/Samsung SSD/hpa-mdo/data/blackcat_004_origin.vsp3",
  "case_dir": "docs/reports/tail_wing_solidification_probe/artifacts/solidification",
  "no_su2_execution": true,
  "no_bl_runtime": true,
  "production_default_changed": false,
  "solidification_status": "no_volume_created",
  "provider_status": "materialized",
  "provider_surface_count": 6,
  "provider_body_count": 0,
  "provider_volume_count": 0,
  "best_output_surface_count": 12,
  "best_output_volume_count": 0,
  "normalized_geometry_path": "/Volumes/Samsung SSD/hpa-mdo/hpa_meshing_package/docs/reports/tail_wing_solidification_probe/artifacts/geometry/artifacts/providers/esp_rebuilt/esp_runtime/normalized.stp",
  "solidification_metadata_path": "docs/reports/tail_wing_solidification_probe/artifacts/solidification/solidification_metadata.json",
  "gmsh_log_path": "docs/reports/tail_wing_solidification_probe/artifacts/solidification/gmsh_log.txt",
  "recommended_next": "explicit_caps_or_baffle_volume_route_required",
  "attempts": [
    {
      "attempt_id": "gmsh_heal_make_solids_1",
      "tolerance": 1e-06,
      "sew_faces": true,
      "make_solids": true,
      "fix_small_edges": true,
      "input_surface_count": 6,
      "input_volume_count": 0,
      "output_surface_count": 12,
      "output_volume_count": 0,
      "healed_entity_count": 211,
      "error": null
    },
    {
      "attempt_id": "gmsh_heal_make_solids_2",
      "tolerance": 1e-05,
      "sew_faces": true,
      "make_solids": true,
      "fix_small_edges": true,
      "input_surface_count": 6,
      "input_volume_count": 0,
      "output_surface_count": 12,
      "output_volume_count": 0,
      "healed_entity_count": 211,
      "error": null
    },
    {
      "attempt_id": "gmsh_heal_make_solids_3",
      "tolerance": 0.0001,
      "sew_faces": true,
      "make_solids": true,
      "fix_small_edges": true,
      "input_surface_count": 6,
      "input_volume_count": 0,
      "output_surface_count": 12,
      "output_volume_count": 0,
      "healed_entity_count": 211,
      "error": null
    },
    {
      "attempt_id": "gmsh_heal_make_solids_4",
      "tolerance": 1e-06,
      "sew_faces": true,
      "make_solids": true,
      "fix_small_edges": false,
      "input_surface_count": 6,
      "input_volume_count": 0,
      "output_surface_count": 12,
      "output_volume_count": 0,
      "healed_entity_count": 211,
      "error": null
    },
    {
      "attempt_id": "gmsh_heal_make_solids_5",
      "tolerance": 1e-05,
      "sew_faces": true,
      "make_solids": true,
      "fix_small_edges": false,
      "input_surface_count": 6,
      "input_volume_count": 0,
      "output_surface_count": 12,
      "output_volume_count": 0,
      "healed_entity_count": 211,
      "error": null
    },
    {
      "attempt_id": "gmsh_heal_make_solids_6",
      "tolerance": 0.0001,
      "sew_faces": true,
      "make_solids": true,
      "fix_small_edges": false,
      "input_surface_count": 6,
      "input_volume_count": 0,
      "output_surface_count": 12,
      "output_volume_count": 0,
      "healed_entity_count": 211,
      "error": null
    }
  ],
  "hpa_mdo_guarantees": [
    "real_vsp3_source_consumed",
    "esp_rebuilt_tail_wing_geometry_materialized",
    "naive_gmsh_heal_make_solids_attempted",
    "mesh_handoff_not_emitted",
    "su2_volume_handoff_not_claimed",
    "production_default_unchanged"
  ],
  "blocking_reasons": [
    "tail_naive_gmsh_heal_solidification_no_volume",
    "tail_surface_only_mesh_not_su2_volume_handoff",
    "tail_wing_solver_not_run",
    "convergence_gate_not_run"
  ],
  "limitations": [
    "mesh_handoff.v1 is not emitted by the solidification probe.",
    "No farfield subtraction or volume mesh is attempted in this probe.",
    "Gmsh heal/sew/makeSolids is evidence only; it is not a production repair policy.",
    "SU2_CFD was not executed.",
    "convergence_gate.v1 was not emitted."
  ],
  "error": null
}
